{
  "rows": [
    {
      "Z": 2.0,
      "n_max": 2,
      "S_B": 0.03954502764024503,
      "w_B_dimless": 0.08223958785144443,
      "delta_B": 0.2634151616856636,
      "n_configs": 7,
      "wall_seconds": 0.0019948482513427734
    },
    {
      "Z": 3.0,
      "n_max": 2,
      "S_B": 0.00935807579829679,
      "w_B_dimless": 0.051221316843156665,
      "delta_B": 0.2631763677708122,
      "n_configs": 7,
      "wall_seconds": 0.0006899833679199219
    },
    {
      "Z": 4.0,
      "n_max": 2,
      "S_B": 0.003862766732545213,
      "w_B_dimless": 0.03744731090284642,
      "delta_B": 0.2631360695301641,
      "n_configs": 7,
      "wall_seconds": 0.0006532669067382812
    },
    {
      "Z": 6.0,
      "n_max": 2,
      "S_B": 0.0013314502132305143,
      "w_B_dimless": 0.024499917019202334,
      "delta_B": 0.2631210930290351,
      "n_configs": 7,
      "wall_seconds": 0.0006215572357177734
    },
    {
      "Z": 10.0,
      "n_max": 2,
      "S_B": 0.00041550733966760434,
      "w_B_dimless": 0.014556504007062291,
      "delta_B": 0.2631178836739179,
      "n_configs": 7,
      "wall_seconds": 0.0006353855133056641
    },
    {
      "Z": 15.0,
      "n_max": 2,
      "S_B": 0.000177360205210867,
      "w_B_dimless": 0.00967440036547994,
      "delta_B": 0.26311750018889113,
      "n_configs": 7,
      "wall_seconds": 0.0006184577941894531
    },
    {
      "Z": 30.0,
      "n_max": 2,
      "S_B": 4.4420090876183455e-05,
      "w_B_dimless": 0.0048282139616929055,
      "delta_B": 0.2631174116919131,
      "n_configs": 7,
      "wall_seconds": 0.0006537437438964844
    },
    {
      "Z": 2.0,
      "n_max": 3,
      "S_B": 0.04081105136647098,
      "w_B_dimless": 0.10443952594881536,
      "delta_B": 0.2009153064866663,
      "n_configs": 31,
      "wall_seconds": 0.018886566162109375
    },
    {
      "Z": 3.0,
      "n_max": 3,
      "S_B": 0.011211717937421746,
      "w_B_dimless": 0.06404631864472168,
      "delta_B": 0.20241900128274115,
      "n_configs": 31,
      "wall_seconds": 0.008275270462036133
    },
    {
      "Z": 4.0,
      "n_max": 3,
      "S_B": 0.004984212431364122,
      "w_B_dimless": 0.046280821558969884,
      "delta_B": 0.20268338965264013,
      "n_configs": 31,
      "wall_seconds": 0.008147716522216797
    },
    {
      "Z": 6.0,
      "n_max": 3,
      "S_B": 0.001817727831328882,
      "w_B_dimless": 0.029989140860709064,
      "delta_B": 0.2027825033906775,
      "n_configs": 31,
      "wall_seconds": 0.008023977279663086
    },
    {
      "Z": 10.0,
      "n_max": 3,
      "S_B": 0.0005855700034359207,
      "w_B_dimless": 0.017714676588318476,
      "delta_B": 0.20280380425589908,
      "n_configs": 31,
      "wall_seconds": 0.008086204528808594
    },
    {
      "Z": 15.0,
      "n_max": 3,
      "S_B": 0.0002530299649626033,
      "w_B_dimless": 0.01172116698147682,
      "delta_B": 0.20280635095188834,
      "n_configs": 31,
      "wall_seconds": 0.008000850677490234
    },
    {
      "Z": 30.0,
      "n_max": 3,
      "S_B": 6.405372314432378e-05,
      "w_B_dimless": 0.005847258151343087,
      "delta_B": 0.20280693869818447,
      "n_configs": 31,
      "wall_seconds": 0.008081674575805664
    },
    {
      "Z": 2.0,
      "n_max": 4,
      "S_B": 0.04187943008973696,
      "w_B_dimless": 0.11054006052203875,
      "delta_B": 0.16243267650655135,
      "n_configs": 101,
      "wall_seconds": 0.27622342109680176
    },
    {
      "Z": 3.0,
      "n_max": 4,
      "S_B": 0.011975181544890363,
      "w_B_dimless": 0.06890817329267976,
      "delta_B": 0.16411559337428253,
      "n_configs": 101,
      "wall_seconds": 0.09306788444519043
    },
    {
      "Z": 4.0,
      "n_max": 4,
      "S_B": 0.005436015305172925,
      "w_B_dimless": 0.049642634842138794,
      "delta_B": 0.16440315553755586,
      "n_configs": 101,
      "wall_seconds": 0.09407329559326172
    },
    {
      "Z": 6.0,
      "n_max": 4,
      "S_B": 0.002016715963703004,
      "w_B_dimless": 0.03186515346708666,
      "delta_B": 0.16451028157159764,
      "n_configs": 101,
      "wall_seconds": 0.09103751182556152
    },
    {
      "Z": 10.0,
      "n_max": 4,
      "S_B": 0.0006564899037704963,
      "w_B_dimless": 0.018742269904751398,
      "delta_B": 0.1645332558459328,
      "n_configs": 101,
      "wall_seconds": 0.09281063079833984
    },
    {
      "Z": 15.0,
      "n_max": 4,
      "S_B": 0.00028489206755359544,
      "w_B_dimless": 0.012414376937174235,
      "delta_B": 0.16453600145896452,
      "n_configs": 101,
      "wall_seconds": 0.09269523620605469
    },
    {
      "Z": 30.0,
      "n_max": 4,
      "S_B": 7.240172450884441e-05,
      "w_B_dimless": 0.006185172146750491,
      "delta_B": 0.16453663507788654,
      "n_configs": 101,
      "wall_seconds": 0.09183168411254883
    },
    {
      "Z": 2.0,
      "n_max": 5,
      "S_B": 0.042358226779866996,
      "w_B_dimless": 0.11170685305492482,
      "delta_B": 0.13564988934851555,
      "n_configs": 266,
      "wall_seconds": 2.517322063446045
    },
    {
      "Z": 3.0,
      "n_max": 5,
      "S_B": 0.012350270454398227,
      "w_B_dimless": 0.07000974059968827,
      "delta_B": 0.1376667343819344,
      "n_configs": 266,
      "wall_seconds": 0.7022569179534912
    },
    {
      "Z": 4.0,
      "n_max": 5,
      "S_B": 0.005660111349237156,
      "w_B_dimless": 0.05069211111419986,
      "delta_B": 0.13801270026896045,
      "n_configs": 266,
      "wall_seconds": 0.6996855735778809
    },
    {
      "Z": 6.0,
      "n_max": 5,
      "S_B": 0.002116458438236263,
      "w_B_dimless": 0.03250679066000424,
      "delta_B": 0.13814169690900602,
      "n_configs": 266,
      "wall_seconds": 0.705873966217041
    },
    {
      "Z": 10.0,
      "n_max": 5,
      "S_B": 0.0006923411849677006,
      "w_B_dimless": 0.018989764422580827,
      "delta_B": 0.13816936978102073,
      "n_configs": 266,
      "wall_seconds": 0.7069904804229736
    },
    {
      "Z": 15.0,
      "n_max": 5,
      "S_B": 0.00030106528139903037,
      "w_B_dimless": 0.012544366956246243,
      "delta_B": 0.13817267711063605,
      "n_configs": 266,
      "wall_seconds": 0.6972141265869141
    },
    {
      "Z": 30.0,
      "n_max": 5,
      "S_B": 7.665660976637065e-05,
      "w_B_dimless": 0.006239730509604055,
      "delta_B": 0.13817344036566648,
      "n_configs": 266,
      "wall_seconds": 0.7024669647216797
    }
  ],
  "local_slopes_Z15_to_30": {
    "2": 1.9920551085553906,
    "3": 1.975458201133946,
    "4": 1.9662292742103888,
    "5": 1.9589180126394723
  }
}